mugo/__init__.py
mugo/core.py
mugo/objectives.py
mugo/utils.py
mugo-0.1.0.dist-info/METADATA
mugo-0.1.0.dist-info/WHEEL
mugo-0.1.0.dist-info/top_level.txt
mugo-0.1.0.dist-info/RECORD
