Metadata-Version: 2.4
Name: mugo
Version: 0.1.0
Summary: Differentiable Combinatorial Optimization for Genomics
Home-page: https://mugo-framework.netlify.app/
Author: SciML Team
Author-email: sciml.open.tools@gmail.com
Classifier: Programming Language :: Python :: 3
Classifier: License :: OSI Approved :: MIT License
Classifier: Operating System :: OS Independent
Requires-Python: >=3.8
Requires-Dist: torch>=2.0
Requires-Dist: pandas
Requires-Dist: numpy
Requires-Dist: pyfaidx
Requires-Dist: borzoi_pytorch
Dynamic: author
Dynamic: author-email
Dynamic: classifier
Dynamic: description
Dynamic: description-content-type
Dynamic: home-page
Dynamic: requires-dist
Dynamic: requires-python
Dynamic: summary
